odoo/addons/disable_login/__init__.py
odoo/addons/disable_login/__manifest__.py
odoo/addons/disable_login/controllers/__init__.py
odoo/addons/disable_login/controllers/main.py
odoo/addons/disable_login/views/auth_templates.xml
odoo_addon_disable_login-16.0.1.0.0.3.dist-info/METADATA
odoo_addon_disable_login-16.0.1.0.0.3.dist-info/WHEEL
odoo_addon_disable_login-16.0.1.0.0.3.dist-info/top_level.txt
odoo_addon_disable_login-16.0.1.0.0.3.dist-info/RECORD
